neurocorgi_sdk/__init__.py
neurocorgi_sdk/transforms.py
neurocorgi_sdk/assets/corgi.jpg
neurocorgi_sdk/models/__init__.py
neurocorgi_sdk/models/neurocorginet.py
neurocorgi_sdk/models/neurocorginet_fq.py
neurocorgi_sdk/models/classification/__init__.py
neurocorgi_sdk/models/classification/imagenet.py
neurocorgi_sdk/models/n2d2/__init__.py
neurocorgi_sdk/models/n2d2/mobilenetv1_quant.py
neurocorgi_sdk/models/n2d2/ncnet_n2d2.py
neurocorgi_sdk/models/n2d2/ncnet_n2d2_torch.py
neurocorgi_sdk/utils/__init__.py
neurocorgi_sdk/utils/checks.py
neurocorgi_sdk-2.0.2.dist-info/LICENSE
neurocorgi_sdk-2.0.2.dist-info/METADATA
neurocorgi_sdk-2.0.2.dist-info/WHEEL
neurocorgi_sdk-2.0.2.dist-info/top_level.txt
neurocorgi_sdk-2.0.2.dist-info/RECORD
