Metadata-Version: 2.1
Name: neurocorgi_sdk
Version: 2.0.2
Summary: NeuroCorgi-SDK to use the NeuroCorgi model in object detection, instance segmentation and image classification apps.
Author: Ivan Miro Panades, Vincent Lorrain, Lilian Billod, Inna Kucher, Vincent Templier
Maintainer: Vincent Templier, Lilian Billod
License: CECILL-2.1
Project-URL: Homepage, https://neurocorgi.com
Project-URL: Source, https://github.com/CEA-LIST/neurocorgi_sdk
Keywords: machine-learning,deep-learning,computer-vision,ML,DL,AI,NeuroCorgi,CEA
Classifier: Development Status :: 5 - Production/Stable
Classifier: Intended Audience :: Developers
Classifier: Intended Audience :: Education
Classifier: Intended Audience :: Science/Research
Classifier: License :: OSI Approved :: CEA CNRS Inria Logiciel Libre License, version 2.1 (CeCILL-2.1)
Classifier: Programming Language :: Python :: 3
Classifier: Programming Language :: Python :: 3.7
Classifier: Programming Language :: Python :: 3.8
Classifier: Programming Language :: Python :: 3.9
Classifier: Programming Language :: Python :: 3.10
Classifier: Programming Language :: Python :: 3.11
Classifier: Topic :: Software Development
Classifier: Topic :: Software Development :: Libraries :: Python Modules
Classifier: Topic :: Scientific/Engineering
Classifier: Topic :: Scientific/Engineering :: Artificial Intelligence
Classifier: Topic :: Scientific/Engineering :: Image Recognition
Classifier: Operating System :: POSIX :: Linux
Classifier: Operating System :: MacOS
Classifier: Operating System :: Microsoft :: Windows
Requires-Python: >=3.7
License-File: LICENSE
Requires-Dist: matplotlib
Requires-Dist: numpy
Requires-Dist: opencv-python
Requires-Dist: pillow
Requires-Dist: safetensors
Requires-Dist: requests
Requires-Dist: scipy
Requires-Dist: torch >=1.8.0
Requires-Dist: torchvision >=0.9.0
Requires-Dist: tqdm
Requires-Dist: pandas
Requires-Dist: seaborn
Provides-Extra: dev
Requires-Dist: ipython ; extra == 'dev'
Requires-Dist: pytest ; extra == 'dev'
Requires-Dist: pytest-cov ; extra == 'dev'
Requires-Dist: onnx ; extra == 'dev'
Provides-Extra: extra
Requires-Dist: ipython ; extra == 'extra'
Requires-Dist: albumentations >=1.0.3 ; extra == 'extra'
Requires-Dist: pycocotools >=2.0.6 ; extra == 'extra'
Requires-Dist: psutil ; extra == 'extra'
Requires-Dist: py-cpuinfo ; extra == 'extra'
Requires-Dist: thop ; extra == 'extra'
